tetunlid/__init__.py
tetunlid/lid.py
tetunlid/model/tetun_lid_model.pkl
tetun_lid-1.1.2.dist-info/METADATA
tetun_lid-1.1.2.dist-info/WHEEL
tetun_lid-1.1.2.dist-info/licenses/LICENSE
tetun_lid-1.1.2.dist-info/RECORD
