Metadata-Version: 2.3
Name: tetun_lid
Version: 1.1.2
Summary: Tetun Language Identification Model
Project-URL: repository, https://github.com/gabriel-de-jesus/tetun-lid
Author-email: Gabriel de Jesus <gabriel.dejesus@timornews.tl>
License-File: LICENSE
Classifier: License :: OSI Approved :: MIT License
Classifier: Operating System :: OS Independent
Classifier: Programming Language :: Python :: 3
Requires-Python: >=3.8
